tailors_fast/__init__.py
tailors_fast/dataset_from_eb.py
tailors_fast/dates.py
tailors_fast/locations.py
tailors_fast/model.py
tailors_fast/split.py
tailors_fast/stopwords.py
tailors_fast/texts.py
tailors_fast/tokenizer.py
tailors_fast/train.py
tailors_fast-0.2.0.dist-info/entry_points.txt
tailors_fast-0.2.0.dist-info/LICENSE
tailors_fast-0.2.0.dist-info/WHEEL
tailors_fast-0.2.0.dist-info/METADATA
tailors_fast-0.2.0.dist-info/RECORD
