Metadata-Version: 2.1
Name: tailors-fast
Version: 0.2.0
Summary: 
Home-page: https://github.com/orctom/tailors-fastatic
License: Apache-2.0
Author: orctom
Author-email: orctom <orctom@gmail.com>
Requires-Python: >=3.8
Requires-Dist: hao>=3.7.11
Requires-Dist: fasttext~=0.9.2
Requires-Dist: jieba~=0.42.1
Requires-Dist: opencc~=1.1.6
Requires-Dist: ftfy~=6.1.1
Requires-Dist: scikit-learn~=1.2.0 ; extra == "dev"
Project-URL: homepage, https://github.com/orctom/tailors-fastatic
Provides-Extra: dev
